Workbook

Sheet Inventario
A1: INVENTARIO DE INFRAESTRUCTURA (CAPEX Y OPEX)
A3: Categoría | B3: Concepto / Equipo | C3: Cant. | D3: Coste Adq. Unidad | E3: Coste Recurrente Anual | F3: Total Adquisición (CAPEX) | G3: Total Recurrente (OPEX)
A4: Puestos de Trabajo | B4: Portátiles empleados | C4: 20 | D4: 850 | E4: 0 | F4: =IF(OR(C4="",D4=""),"",C4*D4) | G4: =IF(OR(C4="",E4=""),"",C4*E4)
A5: Puestos de Trabajo | B5: Monitores y periféricos | C5: 20 | D5: 150 | E5: 0 | F5: =IF(OR(C5="",D5=""),"",C5*D5) | G5: =IF(OR(C5="",E5=""),"",C5*E5)
A6: Redes y Seguridad | B6: Firewall (Hardware + Licencia) | C6: 1 | D6: 900 | E6: 300 | F6: =IF(OR(C6="",D6=""),"",C6*D6) | G6: =IF(OR(C6="",E6=""),"",C6*E6)
A7: Redes y Seguridad | B7: Línea de Internet Fibra | C7: 1 | D7: 0 | E7: 840 | F7: =IF(OR(C7="",D7=""),"",C7*D7) | G7: =IF(OR(C7="",E7=""),"",C7*E7)
A8: Servidores / Cloud | B8: Instancia AWS o Azure | C8: 2 | D8: 0 | E8: 1200 | F8: =IF(OR(C8="",D8=""),"",C8*D8) | G8: =IF(OR(C8="",E8=""),"",C8*E8)
A9: Software General | B9: Licencias Microsoft 365 | C9: 20 | D9: 0 | E9: 144 | F9: =IF(OR(C9="",D9=""),"",C9*D9) | G9: =IF(OR(C9="",E9=""),"",C9*E9)
A10: Software General | B10: CRM / ERP (Suscripción) | C10: 15 | D10: 0 | E10: 600 | F10: =IF(OR(C10="",D10=""),"",C10*D10) | G10: =IF(OR(C10="",E10=""),"",C10*E10)
F11: =IF(OR(C11="",D11=""),"",C11*D11) | G11: =IF(OR(C11="",E11=""),"",C11*E11)
F12: =IF(OR(C12="",D12=""),"",C12*D12) | G12: =IF(OR(C12="",E12=""),"",C12*E12)
F13: =IF(OR(C13="",D13=""),"",C13*D13) | G13: =IF(OR(C13="",E13=""),"",C13*E13)
F14: =IF(OR(C14="",D14=""),"",C14*D14) | G14: =IF(OR(C14="",E14=""),"",C14*E14)
F15: =IF(OR(C15="",D15=""),"",C15*D15) | G15: =IF(OR(C15="",E15=""),"",C15*E15)
F16: =IF(OR(C16="",D16=""),"",C16*D16) | G16: =IF(OR(C16="",E16=""),"",C16*E16)
F17: =IF(OR(C17="",D17=""),"",C17*D17) | G17: =IF(OR(C17="",E17=""),"",C17*E17)
F18: =IF(OR(C18="",D18=""),"",C18*D18) | G18: =IF(OR(C18="",E18=""),"",C18*E18)
F19: =IF(OR(C19="",D19=""),"",C19*D19) | G19: =IF(OR(C19="",E19=""),"",C19*E19)
F20: =IF(OR(C20="",D20=""),"",C20*D20) | G20: =IF(OR(C20="",E20=""),"",C20*E20)
F21: =IF(OR(C21="",D21=""),"",C21*D21) | G21: =IF(OR(C21="",E21=""),"",C21*E21)
F22: =IF(OR(C22="",D22=""),"",C22*D22) | G22: =IF(OR(C22="",E22=""),"",C22*E22)
... F30: =IF(OR(C30="",D30=""),"",C30*D30) | G30: =IF(OR(C30="",E30=""),"",C30*E30)
E31: TOTALES: | F31: =SUM(F4:F30) | G31: =SUM(G4:G30)

Sheet Calculadora TCO
A1: CALCULADORA TCO GLOBAL
A2: Escenario (ver Parámetros) | B2: =Parámetros!B3
A3: Años de proyección (Amortización): | B3: =Parámetros!B6
A5: COSTES DIRECTOS (PRESUPUESTADOS)
A6: Categoría | B6: Concepto | C6: Valor (Unit./Anual) | D6: Cantidad / Años | E6: Total Proyectado (€)
A7: Infraestructura | B7: Inversión Inicial (CAPEX Total) | C7: =Inventario!F31 | D7: 1 | E7: =C7*D7
A8: Infraestructura | B8: Costes Recurrentes (OPEX Total Anual) | C8: =Inventario!G31 | D8: =B3 | E8: =C8*D8
A9: Formación Admin. | B9: Formación (Coste h x Total Horas) | C9: =Parámetros!$B$11 | D9: =Parámetros!$B$10*Parámetros!$B$12 | E9: =C9*D9
A10: Administración | B10: Auditorías / Mantenimientos extra (anual) | C10: =Parámetros!$B$13 | D10: =B3 | E10: =C10*D10
D11: SUBTOTAL DIRECTOS: | E11: =SUM(E7:E10)
A13: COSTES INDIRECTOS (OCULTOS)
A14: Categoría | B14: Concepto | C14: Valor (Unit./Anual) | D14: Cantidad / Años | E14: Total Proyectado (€)
A15: Downtime (Fallos) | B15: Pérdida económica por hora inactividad | C15: =Parámetros!$B$14 | D15: =Parámetros!$B$15*Parámetros!$B$16*B$3 | E15: =C15*D15
A16: Costes de Usuario | B16: Autoaprendizaje usuarios (€/año) | C16: =Parámetros!$B$29 | D16: =B$3 | E16: =C16*D16
A17: Costes de Usuario | B17: Soporte entre compañeros (€/año) | C17: =Parámetros!$B$30 | D17: =B$3 | E17: =C17*D17
D18: SUBTOTAL INDIRECTOS: | E18: =SUM(E15:E17)
A20: COSTE TOTAL DE PROPIEDAD (TCO) PROYECTADO | E20: =E11+E18
A22: KPIs (nominal y VAN)
A23: TCO nominal (Cashflow) | E23: =Cashflow!M15
A24: TCO VAN (descontado) | E24: =Cashflow!N15
A25: Coste medio anual | E25: =IF(B3>0,Cashflow!M15/B3,0)
A26: % Directos (nominal) | E26: =IF(Cashflow!M15>0,Cashflow!M10/Cashflow!M15,0)
A27: % Indirectos (nominal) | E27: =IF(Cashflow!M15>0,Cashflow!M14/Cashflow!M15,0)

Sheet Escenarios
A1: ESCENARIOS (selección rápida de supuestos)
A3: Escenario | B3: Años | C3: Inflación p.a. | D3: Descuento | E3: Usuarios | F3: Admins | G3: Coste hora admin | H3: Horas formación/admin | I3: Auditoría anual | J3: Coste hora downtime | K3: Horas/incidente | L3: Incidentes/año | M3: Autoaprendizaje h/usuario/año | N3: Soporte h/usuario/año | O3: Coste hora usuario
A4: Base | B4: 5 | C4: 0 | D4: 0 | E4: 20 | F4: 2 | G4: 50 | H4: 40 | I4: 0 | J4: 150 | K4: 24 | L4: 4 | M4: 0 | N4: 0 | O4: 30
A5: Optimista | B5: 5 | C5: 0.02 | D5: 0.04 | E5: 20 | F5: 2 | G5: 50 | H5: 30 | I5: 0 | J5: 150 | K5: 8 | L5: 2 | M5: 0 | N5: 0 | O5: 30
A6: Pesimista | B6: 5 | C6: 0.03 | D6: 0.06 | E6: 20 | F6: 2 | G6: 55 | H6: 50 | I6: 500 | J6: 200 | K6: 36 | L6: 8 | M6: 2 | N6: 1 | O6: 35
A8: Edita los valores de cada escenario según tu caso. La hoja 'Parámetros' toma los valores del escenario seleccionado (B3).

Sheet Parámetros
A1: PARÁMETROS DEL MODELO (inputs y supuestos)
A3: Escenario | B3: Base
A5: Parámetro | B5: Valor (editable) | C5: Unidad / Nota | D5: Origen
A6: Años de proyección (N) | B6: =VLOOKUP($B$3,Escenarios!$A$4:$O$6,2,FALSE) | C6: años | D6: Escenarios
A7: Inflación / escalado anual OPEX | B7: =VLOOKUP($B$3,Escenarios!$A$4:$O$6,3,FALSE) | C7: % p.a. | D7: Escenarios
A8: Tasa de descuento (para VAN) | B8: =VLOOKUP($B$3,Escenarios!$A$4:$O$6,4,FALSE) | C8: % | D8: Escenarios
A9: Usuarios (empleados) | B9: =VLOOKUP($B$3,Escenarios!$A$4:$O$6,5,FALSE) | C9: personas | D9: Escenarios
A10: Admins | B10: =VLOOKUP($B$3,Escenarios!$A$4:$O$6,6,FALSE) | C10: personas | D10: Escenarios
A11: Coste hora admin | B11: =VLOOKUP($B$3,Escenarios!$A$4:$O$6,7,FALSE) | C11: €/hora | D11: Escenarios
A12: Horas formación por admin (one-off) | B12: =VLOOKUP($B$3,Escenarios!$A$4:$O$6,8,FALSE) | C12: horas | D12: Escenarios
A13: Auditoría / mantenimiento anual | B13: =VLOOKUP($B$3,Escenarios!$A$4:$O$6,9,FALSE) | C13: €/año | D13: Escenarios
A14: Coste hora downtime | B14: =VLOOKUP($B$3,Escenarios!$A$4:$O$6,10,FALSE) | C14: €/hora | D14: Escenarios
A15: Horas por incidente | B15: =VLOOKUP($B$3,Escenarios!$A$4:$O$6,11,FALSE) | C15: horas | D15: Escenarios
A16: Incidentes por año | B16: =VLOOKUP($B$3,Escenarios!$A$4:$O$6,12,FALSE) | C16: incidentes/año | D16: Escenarios
A17: Horas autoaprendizaje por usuario/año | B17: =VLOOKUP($B$3,Escenarios!$A$4:$O$6,13,FALSE) | C17: h/usuario/año | D17: Escenarios
A18: Horas soporte entre compañeros por usuario/año | B18: =VLOOKUP($B$3,Escenarios!$A$4:$O$6,14,FALSE) | C18: h/usuario/año | D18: Escenarios
A19: Coste hora usuario | B19: =VLOOKUP($B$3,Escenarios!$A$4:$O$6,15,FALSE) | C19: €/hora | D19: Escenarios
A22: Valores vinculados (desde Inventario)
A23: CAPEX total (inventario) | B23: =Inventario!F31
A24: OPEX anual total (inventario) | B24: =Inventario!G31
A26: Cálculos auxiliares (automáticos)
A27: Formación total (one-off) | B27: =B10*B12*B11
A28: Downtime anual (€/año) | B28: =B14*B15*B16
A29: Autoaprendizaje anual (€/año) | B29: =B9*B17*B19
A30: Soporte entre compañeros anual (€/año) | B30: =B9*B18*B19
A32: Tip: puedes sobrescribir cualquier celda de la columna 'Valor' (B) si quieres ajustar manualmente un supuesto (reemplazará la fórmula del escenario).

Sheet Cashflow
A1: CASHFLOW DE COSTES (nominal) Y VAN
A3: Concepto | B3: Año 0 | C3: Año 1 | D3: Año 2 | E3: Año 3 | F3: Año 4 | G3: Año 5 | H3: Año 6 | I3: Año 7 | J3: Año 8 | K3: Año 9 | L3: Año 10 | M3: Total nominal | N3: VAN
A4: (helper) | B4: 0 | C4: 1 | D4: 2 | E4: 3 | F4: 4 | G4: 5 | H4: 6 | I4: 7 | J4: 8 | K4: 9 | L4: 10
A6: CAPEX (inversión inicial) | B6: =Parámetros!$B$23 | C6: 0 | D6: 0 | E6: 0 | F6: 0 | G6: 0 | H6: 0 | I6: 0 | J6: 0 | K6: 0 | L6: 0 | M6: =SUM(B6:L6) | N6: =B6+NPV(Parámetros!$B$8,C6:L6)
A7: OPEX (inventario) anual | B7: 0 | C7: =IF(C$4<=Parámetros!$B$6,Parámetros!$B$24*(1+Parámetros!$B$7)^(C$4-1),0) | D7: =IF(D$4<=Parámetros!$B$6,Parámetros!$B$24*(1+Parámetros!$B$7)^(D$4-1),0) | E7: =IF(E$4<=Parámetros!$B$6,Parámetros!$B$24*(1+Parámetros!$B$7)^(E$4-1),0) | F7: =IF(F$4<=Parámetros!$B$6,Parámetros!$B$24*(1+Parámetros!$B$7)^(F$4-1),0) | G7: =IF(G$4<=Parámetros!$B$6,Parámetros!$B$24*(1+Parámetros!$B$7)^(G$4-1),0) | H7: =IF(H$4<=Parámetros!$B$6,Parámetros!$B$24*(1+Parámetros!$B$7)^(H$4-1),0) | I7: =IF(I$4<=Parámetros!$B$6,Parámetros!$B$24*(1+Parámetros!$B$7)^(I$4-1),0) | J7: =IF(J$4<=Parámetros!$B$6,Parámetros!$B$24*(1+Parámetros!$B$7)^(J$4-1),0) | ... L7: =IF(L$4<=Parámetros!$B$6,Parámetros!$B$24*(1+Parámetros!$B$7)^(L$4-1),0) | M7: =SUM(B7:L7) | N7: =B7+NPV(Parámetros!$B$8,C7:L7)
A8: Formación admins (one-off) | B8: =Parámetros!$B$27 | C8: 0 | D8: 0 | E8: 0 | F8: 0 | G8: 0 | H8: 0 | I8: 0 | J8: 0 | K8: 0 | L8: 0 | M8: =SUM(B8:L8) | N8: =B8+NPV(Parámetros!$B$8,C8:L8)
A9: Auditorías / mantenimiento anual | B9: 0 | C9: =IF(C$4<=Parámetros!$B$6,Parámetros!$B$13*(1+Parámetros!$B$7)^(C$4-1),0) | D9: =IF(D$4<=Parámetros!$B$6,Parámetros!$B$13*(1+Parámetros!$B$7)^(D$4-1),0) | E9: =IF(E$4<=Parámetros!$B$6,Parámetros!$B$13*(1+Parámetros!$B$7)^(E$4-1),0) | F9: =IF(F$4<=Parámetros!$B$6,Parámetros!$B$13*(1+Parámetros!$B$7)^(F$4-1),0) | G9: =IF(G$4<=Parámetros!$B$6,Parámetros!$B$13*(1+Parámetros!$B$7)^(G$4-1),0) | H9: =IF(H$4<=Parámetros!$B$6,Parámetros!$B$13*(1+Parámetros!$B$7)^(H$4-1),0) | I9: =IF(I$4<=Parámetros!$B$6,Parámetros!$B$13*(1+Parámetros!$B$7)^(I$4-1),0) | J9: =IF(J$4<=Parámetros!$B$6,Parámetros!$B$13*(1+Parámetros!$B$7)^(J$4-1),0) | ... L9: =IF(L$4<=Parámetros!$B$6,Parámetros!$B$13*(1+Parámetros!$B$7)^(L$4-1),0) | M9: =SUM(B9:L9) | N9: =B9+NPV(Parámetros!$B$8,C9:L9)
A10: SUBTOTAL DIRECTOS | B10: =B6+B8 | C10: =C7+C9 | D10: =D7+D9 | E10: =E7+E9 | F10: =F7+F9 | G10: =G7+G9 | H10: =H7+H9 | I10: =I7+I9 | J10: =J7+J9 | ... L10: =L7+L9 | M10: =SUM(B10:L10) | N10: =B10+NPV(Parámetros!$B$8,C10:L10)
A11: Downtime (coste anual) | B11: 0 | C11: =IF(C$4<=Parámetros!$B$6,Parámetros!$B$28*(1+Parámetros!$B$7)^(C$4-1),0) | D11: =IF(D$4<=Parámetros!$B$6,Parámetros!$B$28*(1+Parámetros!$B$7)^(D$4-1),0) | E11: =IF(E$4<=Parámetros!$B$6,Parámetros!$B$28*(1+Parámetros!$B$7)^(E$4-1),0) | F11: =IF(F$4<=Parámetros!$B$6,Parámetros!$B$28*(1+Parámetros!$B$7)^(F$4-1),0) | G11: =IF(G$4<=Parámetros!$B$6,Parámetros!$B$28*(1+Parámetros!$B$7)^(G$4-1),0) | H11: =IF(H$4<=Parámetros!$B$6,Parámetros!$B$28*(1+Parámetros!$B$7)^(H$4-1),0) | I11: =IF(I$4<=Parámetros!$B$6,Parámetros!$B$28*(1+Parámetros!$B$7)^(I$4-1),0) | J11: =IF(J$4<=Parámetros!$B$6,Parámetros!$B$28*(1+Parámetros!$B$7)^(J$4-1),0) | ... L11: =IF(L$4<=Parámetros!$B$6,Parámetros!$B$28*(1+Parámetros!$B$7)^(L$4-1),0) | M11: =SUM(B11:L11) | N11: =B11+NPV(Parámetros!$B$8,C11:L11)
A12: Autoaprendizaje usuarios (coste anual) | B12: 0 | C12: =IF(C$4<=Parámetros!$B$6,Parámetros!$B$29*(1+Parámetros!$B$7)^(C$4-1),0) | D12: =IF(D$4<=Parámetros!$B$6,Parámetros!$B$29*(1+Parámetros!$B$7)^(D$4-1),0) | E12: =IF(E$4<=Parámetros!$B$6,Parámetros!$B$29*(1+Parámetros!$B$7)^(E$4-1),0) | F12: =IF(F$4<=Parámetros!$B$6,Parámetros!$B$29*(1+Parámetros!$B$7)^(F$4-1),0) | G12: =IF(G$4<=Parámetros!$B$6,Parámetros!$B$29*(1+Parámetros!$B$7)^(G$4-1),0) | H12: =IF(H$4<=Parámetros!$B$6,Parámetros!$B$29*(1+Parámetros!$B$7)^(H$4-1),0) | I12: =IF(I$4<=Parámetros!$B$6,Parámetros!$B$29*(1+Parámetros!$B$7)^(I$4-1),0) | J12: =IF(J$4<=Parámetros!$B$6,Parámetros!$B$29*(1+Parámetros!$B$7)^(J$4-1),0) | ... L12: =IF(L$4<=Parámetros!$B$6,Parámetros!$B$29*(1+Parámetros!$B$7)^(L$4-1),0) | M12: =SUM(B12:L12) | N12: =B12+NPV(Parámetros!$B$8,C12:L12)
A13: Soporte entre compañeros (coste anual) | B13: 0 | C13: =IF(C$4<=Parámetros!$B$6,Parámetros!$B$30*(1+Parámetros!$B$7)^(C$4-1),0) | D13: =IF(D$4<=Parámetros!$B$6,Parámetros!$B$30*(1+Parámetros!$B$7)^(D$4-1),0) | E13: =IF(E$4<=Parámetros!$B$6,Parámetros!$B$30*(1+Parámetros!$B$7)^(E$4-1),0) | F13: =IF(F$4<=Parámetros!$B$6,Parámetros!$B$30*(1+Parámetros!$B$7)^(F$4-1),0) | G13: =IF(G$4<=Parámetros!$B$6,Parámetros!$B$30*(1+Parámetros!$B$7)^(G$4-1),0) | H13: =IF(H$4<=Parámetros!$B$6,Parámetros!$B$30*(1+Parámetros!$B$7)^(H$4-1),0) | I13: =IF(I$4<=Parámetros!$B$6,Parámetros!$B$30*(1+Parámetros!$B$7)^(I$4-1),0) | J13: =IF(J$4<=Parámetros!$B$6,Parámetros!$B$30*(1+Parámetros!$B$7)^(J$4-1),0) | ... L13: =IF(L$4<=Parámetros!$B$6,Parámetros!$B$30*(1+Parámetros!$B$7)^(L$4-1),0) | M13: =SUM(B13:L13) | N13: =B13+NPV(Parámetros!$B$8,C13:L13)
A14: SUBTOTAL INDIRECTOS | B14: 0 | C14: =C11+C12+C13 | D14: =D11+D12+D13 | E14: =E11+E12+E13 | F14: =F11+F12+F13 | G14: =G11+G12+G13 | H14: =H11+H12+H13 | I14: =I11+I12+I13 | J14: =J11+J12+J13 | ... L14: =L11+L12+L13 | M14: =SUM(B14:L14) | N14: =B14+NPV(Parámetros!$B$8,C14:L14)
A15: TCO TOTAL | B15: =B10+B14 | C15: =C10+C14 | D15: =D10+D14 | E15: =E10+E14 | F15: =F10+F14 | G15: =G10+G14 | H15: =H10+H14 | I15: =I10+I14 | ... L15: =L10+L14 | M15: =SUM(B15:L15) | N15: =B15+NPV(Parámetros!$B$8,C15:L15)
A17: Nota: Los años > N se calculan como 0 automáticamente. El VAN usa la tasa de descuento definida en Parámetros.

Sheet Dashboard
A1: DASHBOARD TCO
A3: TCO nominal | B3: =Cashflow!M15 | D3: Directos (nominal) | E3: =Cashflow!M10
A4: TCO (VAN) | B4: =Cashflow!N15 | D4: Indirectos (nominal) | E4: =Cashflow!M14
A5: Coste medio anual | B5: =IF(Parámetros!B6>0,B3/Parámetros!B6,0)
A6: % Directos | B6: =IF(B3>0,Cashflow!M10/B3,0)
A7: % Indirectos | B7: =IF(B3>0,Cashflow!M14/B3,0)
A20: Año | B20: Coste total
A21: 0 | B21: =IF(Parámetros!$B$6>=0,Cashflow!B$15,NA())
A22: 1 | B22: =IF(Parámetros!$B$6>=1,Cashflow!C$15,NA())
A23: 2 | B23: =IF(Parámetros!$B$6>=2,Cashflow!D$15,NA())
A24: 3 | B24: =IF(Parámetros!$B$6>=3,Cashflow!E$15,NA())
A25: 4 | B25: =IF(Parámetros!$B$6>=4,Cashflow!F$15,NA())
A26: 5 | B26: =IF(Parámetros!$B$6>=5,Cashflow!G$15,NA())
A27: 6 | B27: =IF(Parámetros!$B$6>=6,Cashflow!H$15,NA())
A28: 7 | B28: =IF(Parámetros!$B$6>=7,Cashflow!I$15,NA())
A29: 8 | B29: =IF(Parámetros!$B$6>=8,Cashflow!J$15,NA())
A30: 9 | B30: =IF(Parámetros!$B$6>=9,Cashflow!K$15,NA())
A31: 10 | B31: =IF(Parámetros!$B$6>=10,Cashflow!L$15,NA())
A33: Tip: ajusta el escenario en Parámetros!B3 o edita los supuestos directamente para ver el impacto inmediato en el TCO.

Sheet ROI
A1: ROI (opcional) — comparar TCO vs ahorros/beneficios
A3: TCO (VAN) del proyecto | B3: =Dashboard!B4
A5: Ahorro / beneficio anual estimado | B5: 0
A6: Años de análisis | B6: =Parámetros!B6
A7: Tasa de descuento (para VAN) | B7: =Parámetros!B8
A9: Beneficio total (nominal) | B9: =B5*B6
A10: ROI (nominal) | B10: =IF(B3>0,(B9-B3)/B3,0)
A11: Payback (años) | B11: =IF(B5>0,B3/B5,"")
A13: VAN de ahorros - TCO (VAN) | B13: =NPV($B$7,B16:B25)-$B$3
A15: Año | B15: Ahorro
A16: 1 | B16: =IF($B$6>=1,$B$5,0)
A17: 2 | B17: =IF($B$6>=2,$B$5,0)
A18: 3 | B18: =IF($B$6>=3,$B$5,0)
A19: 4 | B19: =IF($B$6>=4,$B$5,0)
A20: 5 | B20: =IF($B$6>=5,$B$5,0)
A21: 6 | B21: =IF($B$6>=6,$B$5,0)
A22: 7 | B22: =IF($B$6>=7,$B$5,0)
A23: 8 | B23: =IF($B$6>=8,$B$5,0)
A24: 9 | B24: =IF($B$6>=9,$B$5,0)
A25: 10 | B25: =IF($B$6>=10,$B$5,0)
A27: Introduce un ahorro anual (B5) para obtener ROI, payback y VAN de la inversión.
